MANIFEST.in
setup.cfg
setup.py
pterraform/__init__.py
pterraform/terraform.py
pterraform.egg-info/PKG-INFO
pterraform.egg-info/SOURCES.txt
pterraform.egg-info/dependency_links.txt
pterraform.egg-info/not-zip-safe
pterraform.egg-info/pbr.json
pterraform.egg-info/top_level.txt