Metadata-Version: 1.0
Name: pterraform
Version: 0.1.2
Summary: Terraform wrapper for Python
Home-page: https://github.com/jrbudnack/pterraform
Author: Jeremy Budnack
Author-email: UNKNOWN
License: UNKNOWN
Platform: UNKNOWN
